[
  {
    "name": "water",
    "color": {
      "r": 0,
      "g": 162,
      "b": 232
    }
  },
  {
    "name": "Древний Китай",
    "color": {
      "r": 192,
      "g": 192,
      "b": 192
    }
  },
  {
    "name": "Древняя Греция",
    "color": {
      "r": 128,
      "g": 64,
      "b": 64
    }
  },
  {
    "name": "Римское царство",
    "color": {
      "r": 255,
      "g": 0,
      "b": 128
    }
  },
  {
    "name": "Египет",
    "color": {
      "r": 255,
      "g": 128,
      "b": 0
    }
  },
  {
    "name": "Персия",
    "color": {
      "r": 0,
      "g": 255,
      "b": 255
    }
  }
]